livinglooper/__init__.py
livinglooper/__main__.py
livinglooper/dummy.py
livinglooper/export.py
livinglooper/loop.py
livinglooper/model.py
livinglooper/representation.py
livinglooper/tfr.py
livinglooper/transform.py
livinglooper-0.1.0.dist-info/LICENSE
livinglooper-0.1.0.dist-info/METADATA
livinglooper-0.1.0.dist-info/WHEEL
livinglooper-0.1.0.dist-info/entry_points.txt
livinglooper-0.1.0.dist-info/RECORD
