Metadata-Version: 2.1
Name: livinglooper
Version: 0.1.0
Summary: The Living Looper is a software musical instrument using neural synthesis.
License: MIT
Author: Victor Shepardson
Author-email: victor.shepardson@gmail.com
Requires-Python: >=3.10,<3.13
Classifier: License :: OSI Approved :: MIT License
Classifier: Programming Language :: Python :: 3
Classifier: Programming Language :: Python :: 3.10
Classifier: Programming Language :: Python :: 3.11
Classifier: Programming Language :: Python :: 3.12
Requires-Dist: fire (>=0.7.0,<0.8.0)
Requires-Dist: nn-tilde (>=1.5.6,<2.0.0)
Requires-Dist: numpy (>=1.23,<2.0)
Requires-Dist: termcolor (>=2.5.0,<3.0.0)
Requires-Dist: torch (>=1.13,<2.3)
Requires-Dist: tqdm (>=4.64,<5.0)
